yaml_syntax/__init__.py
yaml_syntax/exception_handler.py
yaml_syntax/exceptions.py
yaml_syntax/syntax.py
yaml_syntax-0.0.9.dist-info/licenses/LICENSE
yaml_syntax-0.0.9.dist-info/METADATA
yaml_syntax-0.0.9.dist-info/WHEEL
yaml_syntax-0.0.9.dist-info/top_level.txt
yaml_syntax-0.0.9.dist-info/RECORD
