Metadata-Version: 2.4
Name: yaml-syntax
Version: 0.0.9
Summary: Check the syntax of a YAML file as you want to be. Checking the syntax of the YAML file is based on BaseModel of Pydantic.
Author-email: EmadDeve20 <emaddeve20@gmail.com>
Maintainer-email: EmadDeve20 <emaddeve20@gmail.com>
License-Expression: GPL-3.0-or-later
Project-URL: Homepage, https://github.com/EmadDeve20/yaml-syntax
Project-URL: Repository, https://github.com/EmadDeve20/yaml-syntax
Project-URL: Issues, https://github.com/EmadDeve20/yaml-syntax/issues
Keywords: yaml,syntax,pydantic
Classifier: Development Status :: 1 - Planning
Classifier: Programming Language :: Python :: 3.10
Requires-Python: >=3.10
License-File: LICENSE
Requires-Dist: PyYAML>=6.0.3
Requires-Dist: pydantic>=2.12.3
Dynamic: license-file
